{
  "exam_name": "2019年考研数学（一）真题",
  "questions": [
    {
      "question_number": "1",
      "question_body": "当 $x \\to 0$ 时, 若 $x - \\tan x$ 与 $x^k$ 是同阶无穷小, 则 $k = ($ )",
      "options": {
        "A": "1",
        "B": "2",
        "C": "3",
        "D": "4"
      },
      "analysis": {
        "primary_knowledge_point": "等价无穷小替换：$\\tan x \\sim x + \\frac{x^3}{3} + o(x^3)$",
        "secondary_knowledge_points": [
          "泰勒展开",
          "无穷小阶的比较"
        ],
        "question_type": "无穷小阶的比较题",
        "methodology_and_tricks": "对$\\tan x$进行泰勒展开至三阶项，然后与$x$相减，通过比较确定主项的阶数。",
        "common_pitfalls": "展开精度不足，例如只展开到$x$项导致$x - \\tan x \\sim x - x = 0$，得出错误的阶数。",
        "computational_workload": "低"
      },
      "is_multiple_choice": true
    },
    {
      "question_number": "2",
      "question_body": "设函数 $f(x) = \\begin{cases} \\frac{x|x|}{1 - \\cos x}, & x \\le 0 \\\\ x \\ln x, & x > 0 \\end{cases}$, 则 $x = 0$ 是 $f(x)$ 的($$)",
      "options": {
        "A": "可导点, 极值点.",
        "B": "不可导点, 极值点.",
        "C": "可导点, 非极值点.",
        "D": "不可导点, 非极值点."
      },
      "analysis": {
        "primary_knowledge_point": "导数在一点的定义及判断原理",
        "secondary_knowledge_points": [
          "分段函数在分段点的导数",
          "左右导数的计算",
          "函数极值点的第一充分条件",
          "等价无穷小替换 (例如 1-cosx ~ x^2/2)",
          "极限的计算"
        ],
        "question_type": "分段函数在分段点的可导性与极值点判别",
        "methodology_and_tricks": "题眼在于分别计算函数在 x=0 处的左导数 f'_-(0) 和右导数 f'_+(0)。利用导数定义和等价无穷小替换，精确计算两个极限。对于极值的判断，则需考察该点邻域内函数值的变化情况。",
        "common_pitfalls": "1. 在计算左导数时，未能正确处理绝对值 |x| 在 x<0 时为 -x，导致符号错误。2. 在利用等价无穷小 1-cosx ~ x^2/2 时，忽略系数或因式分解错误。3. 在判断极值点时，仅凭感觉或函数在孤立点的值，而没有严格考察其左右邻域内函数值的符号变化。",
        "computational_workload": "中"
      },
      "is_multiple_choice": true
    },
    {
      "question_number": "3",
      "question_body": "设 $\\{u_n\\}$ 是单调增加的有界数列, 则下列级数中收敛的是($$)",
      "options": {
        "A": "$\\sum_{n=1}^{\\infty} \\frac{u_n}{n}.$",
        "B": "$\\sum_{n=1}^{\\infty} (-1)^n \\frac{1}{u_n}.$",
        "C": "$\\sum_{n=1}^{\\infty} \\left(1 - \\frac{u_n}{u_{n+1}}\\right).$",
        "D": "$\\sum_{n=1}^{\\infty} (u_{n+1}^2 - u_n^2).$"
      },
      "analysis": {
        "primary_knowledge_point": "正项级数的比较判别法及极限形式",
        "secondary_knowledge_points": [
          "单调有界数列及其极限存在性",
          "绝对收敛与交错级数",
          "级数收敛的必要条件",
          "裂项相消求和法"
        ],
        "question_type": "无穷级数敛散性判别",
        "methodology_and_tricks": "本题的题眼在于利用一个单调递增有界的正项数列{u_n}的性质。对于选项C，通过构造比较对象，将1 - u_n/u_{n+1}与(u_{n+1} - u_n)联系起来，再利用单调有界数列的收敛性，通过比较判别法证明其收敛。",
        "common_pitfalls": "考生容易错误地认为u_n单调递增有界，则其对应的正项级数一定收敛，从而误选A；或者在没有验证u_n不趋于0的情况下（交错级数Leibniz判别法要求通项趋于0）误用交错级数判别法而误选B；对于D选项，未能识别其可裂项求和从而得到部分和序列有极限（即级数收敛）。",
        "computational_workload": "中"
      },
      "is_multiple_choice": true
    },
    {
      "question_number": "4",
      "question_body": "设函数 $Q(x,y) = \\frac{x}{y^2}$. 如果对上半平面 $(y > 0)$ 内的任意有向光滑封闭曲线 $C$ 都有 $\\oint_C P(x,y)dx + Q(x,y)dy = 0$, 那么函数 $P(x,y)$ 可取为($$)",
      "options": {
        "A": "$y - \\frac{x^2}{y^3}.$",
        "B": "$y - \\frac{1}{y}.$",
        "C": "$1 - \\frac{1}{x}.$",
        "D": "$x - \\frac{1}{y}.$"
      },
      "analysis": {
        "primary_knowledge_point": "曲线积分与路径无关的等价条件",
        "secondary_knowledge_points": [
          "格林公式",
          "偏导数的计算",
          "二元函数全微分的原函数求解"
        ],
        "question_type": "曲线积分性质与路径无关性判定题",
        "methodology_and_tricks": "利用曲线积分与路径无关的充要条件：∂P/∂y ≡ ∂Q/∂x（在单连通区域内）。先由给定Q(x,y)求出∂Q/∂x，再令其等于∂P/∂y，通过积分求出P(x,y)的一般形式。",
        "common_pitfalls": "忽略题目中“上半平面(y>0)”这一单连通区域条件；在积分求P(x,y)时遗漏关于x的任意函数项；未验证选项是否满足∂P/∂y = ∂Q/∂x。",
        "computational_workload": "中"
      },
      "is_multiple_choice": true
    },
    {
      "question_number": "5",
      "question_body": "设 $\\mathbf{A}$ 是 $3$ 阶实对称矩阵, $\\mathbf{E}$ 是 $3$ 阶单位矩阵. 若 $\\mathbf{A}^2 + \\mathbf{A} = 2\\mathbf{E}$, 且 $|\\mathbf{A}| = 4$, 则二次型 $\\boldsymbol{x}^{\\mathrm{T}} \\mathbf{A} \\boldsymbol{x}$ 的规范形为($$)",
      "options": {
        "A": "$y_1^2 + y_2^2 + y_3^2.$",
        "B": "$y_1^2 + y_2^2 - y_3^2.$",
        "C": "$y_1^2 - y_2^2 - y_3^2.$",
        "D": "$-y_1^2 - y_2^2 - y_3^2.$"
      },
      "analysis": {
        "primary_knowledge_point": "矩阵特征值与二次型规范形的确定",
        "secondary_knowledge_points": [
          "实对称矩阵的性质",
          "特征值与特征方程的关系",
          "行列式与特征值的关系",
          "二次型规范形的定义"
        ],
        "question_type": "二次型规范形判定题",
        "methodology_and_tricks": "题眼在于利用矩阵方程 A² + A = 2E 推导出特征值满足的方程 λ² + λ - 2 = 0，解得可能特征值为 1 和 -2。再结合 |A| = 4 这一条件确定特征值的具体分布（重数），从而确定二次型的正负惯性指数。",
        "common_pitfalls": "1. 忽略实对称矩阵必可相似对角化且规范形由特征值符号决定这一关键点。2. 由 |A|=4 推导特征值组合时，未能正确判断特征值-2的重数（例如错误地认为两个特征值为1，一个为-2，则行列式为-4≠4）。3. 混淆矩阵的秩、迹与行列式在确定特征值时的作用。",
        "computational_workload": "低"
      },
      "is_multiple_choice": true
    },
    {
      "question_number": "6",
      "question_body": "如图所示, 有 $3$ 张平面两两相交, 交线相互平行, 它们的方程 $a_{i1}x + a_{i2}y + a_{i3}z = d_i (i=1, 2, 3)$ 组成的线性方程组的系数矩阵和增广矩阵分别记为 $\\mathbf{A}, \\overline{\\mathbf{A}}$, 则($$)",
      "options": {
        "A": "$r(\\mathbf{A}) = 2, r(\\overline{\\mathbf{A}}) = 3.$",
        "B": "$r(\\mathbf{A}) = 2, r(\\overline{\\mathbf{A}}) = 2.$",
        "C": "$r(\\mathbf{A}) = 1, r(\\overline{\\mathbf{A}}) = 2.$",
        "D": "$r(\\mathbf{A}) = 1, r(\\overline{\\mathbf{A}}) = 1.$"
      },
      "analysis": {
        "primary_knowledge_point": "线性方程组解的判定（r(A)与r(Ā)的关系与几何意义的对应）",
        "secondary_knowledge_points": [
          "空间平面方程及其法向量",
          "向量组的秩与线性相关性",
          "平面间的位置关系（平行、相交）"
        ],
        "question_type": "线性方程组理论（几何应用）选择题",
        "methodology_and_tricks": "题眼在于将抽象的矩阵秩与具体的空间几何位置关系对应。三个平面两两相交且交线平行，意味着它们的法向量共面（线性相关），但不平行于同一平面（方程组有解），从而确定 r(A)=2；同时，三个平面不共面（无公共交点），意味着方程组不相容，从而 r(Ā)=3。",
        "common_pitfalls": "1. 错误地将‘交线相互平行’理解为三个平面平行（导致误判r(A)=1）。2. 混淆‘两两相交’与‘三面共线’（导致误判r(Ā)=2）。3. 未能建立矩阵秩的代数定义与空间几何直观的联系。",
        "computational_workload": "低"
      },
      "is_multiple_choice": true
    },
    {
      "question_number": "7",
      "question_body": "设 $A, B$ 为随机事件, 则 $P(A) = P(B)$ 的充分必要条件是($$)",
      "options": {
        "A": "$P(A \\cup B) = P(A) + P(B).$",
        "B": "$P(AB) = P(A)P(B).$",
        "C": "$P(A \\overline{B}) = P(B \\overline{A}).$",
        "D": "$P(\\overline{A}) = P(\\overline{B}).$"
      },
      "analysis": {
        "primary_knowledge_point": "随机事件概率的等式关系及事件间的互斥与对立关系",
        "secondary_knowledge_points": [
          "概率的加法公式",
          "对立事件概率",
          "概率的互斥性"
        ],
        "question_type": "随机事件概率的充分必要条件判断",
        "methodology_and_tricks": "题眼在于分析选项中的等式是否蕴含或等价于 P(A) = P(B)。对于选项C，可以改写为 P(A) - P(AB) = P(B) - P(AB)，从而直接推出 P(A) = P(B)；对于其他选项，可以通过构造反例或分析其等价条件来排除。",
        "common_pitfalls": "误以为事件互斥（选项A）或独立（选项B）就能推出概率相等；误以为对立事件概率相等（选项D）能推出原事件概率相等（实际上这总是成立，不能作为充分必要条件）。",
        "computational_workload": "低"
      },
      "is_multiple_choice": true
    },
    {
      "question_number": "8",
      "question_body": "设随机变量 $X$ 与 $Y$ 相互独立, 且都服从正态分布 $N(\\mu, \\sigma^2)$, 则 $P\\{|X - Y| < 1\\}$($$)",
      "options": {
        "A": "与 $\\mu$ 无关, 而与 $\\sigma^2$ 有关.",
        "B": "与 $\\mu$ 有关, 而与 $\\sigma^2$ 无关.",
        "C": "与 $\\mu, \\sigma^2$ 都有关.",
        "D": "与 $\\mu, \\sigma^2$ 都无关."
      },
      "analysis": {
        "primary_knowledge_point": "两个独立正态随机变量之差的分布：若 X ~ N(μ₁, σ²), Y ~ N(μ₂, σ²) 且相互独立，则 X - Y ~ N(μ₁ - μ₂, 2σ²)。",
        "secondary_knowledge_points": [
          "正态分布的标准化",
          "概率的基本计算 P(|U|<1) 其中 U 为标准正态变量",
          "随机变量独立性的应用"
        ],
        "question_type": "概率计算与正态分布性质判断题",
        "methodology_and_tricks": "利用独立正态变量之差仍为正态分布的性质，将问题转化为计算一个服从 N(0, 2σ²) 的随机变量的绝对值概率，再通过标准化说明其只与 σ² 有关。",
        "common_pitfalls": "误认为均值 μ 会影响两个同分布正态变量之差的分布（实际上差值的均值恒为0），或未正确计算出差值分布的方差为 2σ²。",
        "computational_workload": "低"
      },
      "is_multiple_choice": true
    },
    {
      "question_number": "9",
      "question_body": "设函数 $f(u)$ 可导，$z = f(\\sin y - \\sin x) + xy$，则 $\\frac{1}{\\cos x} \\cdot \\frac{\\partial z}{\\partial x} + \\frac{1}{\\cos y} \\frac{\\partial z}{\\partial y} = $______.",
      "options": {},
      "analysis": {
        "primary_knowledge_point": "多元复合函数求导的链式法则",
        "secondary_knowledge_points": [
          "偏导数的计算",
          "导数的四则运算法则（乘积法则）",
          "三角函数导数（正弦、余弦）"
        ],
        "question_type": "多元函数偏导数计算题",
        "methodology_and_tricks": "题目的关键在于正确运用链式法则分别求出偏导数 ∂z/∂x 和 ∂z/∂y。首先将中间变量设为 u = sin y - sin x，则 z = f(u) + xy。求解时需注意对 xy 项的偏导（如 ∂(xy)/∂x = y，∂(xy)/∂y = x）以及对复合函数 f(u) 的偏导（如 ∂f/∂x = f'(u) * ∂u/∂x = f'(u) * (-cos x)）。将两个偏导数的表达式代入题目给定的组合中，会发现含有 f'(u) 的项相互抵消，最终得到一个简洁的常数结果。",
        "common_pitfalls": "1. 在应用链式法则时混淆自变量与中间变量，导致对 f(u) 求导错误。例如，误将 ∂f/∂x 写成 f'(x) 而不是 f'(u) * ∂u/∂x。2. 在求 u = sin y - sin x 对 x 或 y 的偏导数时出现符号错误，特别是 ∂u/∂x = -cos x 容易遗漏负号。3. 忽略或错误计算显式项 xy 的偏导数（∂(xy)/∂x = y, ∂(xy)/∂y = x）。",
        "computational_workload": "低"
      },
      "is_multiple_choice": false
    },
    {
      "question_number": "10",
      "question_body": "微分方程 $2yy' - y^2 - 2 = 0$ 满足条件 $y(0) = 1$ 的特解 $y = $______.",
      "options": {},
      "analysis": {
        "primary_knowledge_point": "一阶微分方程求解（可化为可分离变量或伯努利方程）",
        "secondary_knowledge_points": [
          "可分离变量法",
          "一阶线性非齐次微分方程求解公式（常数变易法）",
          "指数函数的积分与化简"
        ],
        "question_type": "一阶微分方程求解题",
        "methodology_and_tricks": "通过观察发现方程 $2yy' - y^2 - 2 = 0$ 可以转化为关于 $u = y^2$ 的一阶线性微分方程。这是求解的关键步骤（题眼）。具体而言，令 $u = y^2$，则 $u' = 2yy'$，原方程化为 $u' - u - 2 = 0$，这是一个标准的线性方程，易于求解。",
        "common_pitfalls": "1. 未能识别出 $2yy'$ 是 $y^2$ 的导数，从而错失将方程线性化的最佳方法，试图直接分离变量导致计算复杂或出错。2. 在求解出通解后，代入初始条件 $y(0)=1$ 时，忽略 $y^2 = e^x + 2e^x$ 导致 $y = \text{±}\text{√}(e^x + 2e^x)$ 的符号选择问题，应根据初始条件 $y(0)=1>0$ 选取正根。3. 代数运算错误，特别是在对线性方程 $u' - u = 2$ 应用积分因子 $e^{-x}$ 后的积分和化简过程中。",
        "computational_workload": "中"
      },
      "is_multiple_choice": false
    },
    {
      "question_number": "11",
      "question_body": "幂级数 $\\sum_{n=0}^{\\infty} \\frac{(-1)^n}{(2n)!}x^n$ 在 $(0, +\\infty)$ 内的和函数 $S(x) = $______.",
      "options": {},
      "analysis": {
        "primary_knowledge_point": "幂级数的和函数求解",
        "secondary_knowledge_points": [
          "常见麦克劳林级数展开式（尤其是余弦函数）",
          "幂级数的收敛域"
        ],
        "question_type": "幂级数求和函数",
        "methodology_and_tricks": "将幂级数的一般项与余弦函数的麦克劳林展开式进行比较。关键在于识别出在余弦展开式 $\\cos x = \\sum_{n=0}^{\\infty} \\frac{(-1)^n}{(2n)!} x^{2n}$ 中，指数是 2n，而题目中指数是 n。因此，需要进行变量替换，令 $t = \\sqrt{x}$ 或直接观察出 $S(x) = \\cos(\\sqrt{x})$。",
        "common_pitfalls": "1. 未能正确关联余弦函数的展开式，尤其是忽略指数从 2n 到 n 的变化。2. 没有考虑定义域 $(0, +\\infty)$，对于 $x=0$ 的情况，$\\sqrt{x}$ 在级数中的处理需要单独说明，但题目限定在开区间，故可回避。3. 在变量替换后忘记将变量换回原变量 x。",
        "computational_workload": "低"
      },
      "is_multiple_choice": false
    },
    {
      "question_number": "12",
      "question_body": "设 $\\Sigma$ 设为曲面 $x^2 + y^2 + 4z^2 = 4(z \\ge 0)$ 的上侧，则 $\\iint_{\\Sigma} \\sqrt{4 - x^2 - 4z^2} dxdy = $______.",
      "options": {},
      "analysis": {
        "primary_knowledge_point": "对坐标的曲面积分（第二类曲面积分）的计算方法与投影法",
        "secondary_knowledge_points": [
          "曲面的定向（上侧）",
          "曲面在坐标平面上的投影",
          "曲面积分与二重积分的转换关系",
          "椭球面方程及其几何性质"
        ],
        "question_type": "曲面积分计算题",
        "methodology_and_tricks": "题眼在于识别被积表达式为√(4 - x² - 4z²)，这恰好暗示了将曲面积分向xOy坐标平面投影。解题关键是利用曲面方程x² + y² + 4z² = 4和z ≥ 0，将积分转换为在xOy平面上投影区域D_xy上的二重积分。",
        "common_pitfalls": "最常见错误是忽视曲面的定向（上侧）与投影方向的一致性，导致符号错误；另一个易错点是投影区域的确定不准确，未能正确从曲面方程解出投影区域x² + y² ≤ 4。",
        "computational_workload": "低"
      },
      "is_multiple_choice": false
    },
    {
      "question_number": "13",
      "question_body": "设 $\\mathbf{A} = (\\boldsymbol{\\alpha}_1, \\boldsymbol{\\alpha}_2, \\boldsymbol{\\alpha}_3)$ 为 $3$ 阶矩阵. 若 $\\boldsymbol{\\alpha}_1, \\boldsymbol{\\alpha}_2$ 线性无关，且 $\\boldsymbol{\\alpha}_3 = - \\boldsymbol{\\alpha}_1 + 2\\boldsymbol{\\alpha}_2$，则线性方程组 $\\mathbf{A}\\mathbf{x} = \\mathbf{0}$ 的通解为______.",
      "options": {},
      "analysis": {
        "primary_knowledge_point": "齐次线性方程组解的结构（$\\mathbf{A}\\mathbf{x}=\\mathbf{0}$的通解）",
        "secondary_knowledge_points": [
          "矩阵的列向量组",
          "向量组的线性相关性",
          "矩阵的秩"
        ],
        "question_type": "线性方程组求解题",
        "methodology_and_tricks": "题眼在于利用向量关系式 $\\boldsymbol{\\alpha}_3 = - \\boldsymbol{\\alpha}_1 + 2\\boldsymbol{\\alpha}_2$ 直接确定矩阵$\\mathbf{A}$的秩$r(\\mathbf{A})=2$，进而得到基础解系所含向量个数为$n-r=3-2=1$。通解由一个特解（即表示$\\boldsymbol{\\alpha}_3$的系数向量）乘以任意常数构成。",
        "common_pitfalls": "最常见的错误是忽略通解形式应为$k\\mathbf{x}_0$（$k$为任意常数），而只写出特解$\\mathbf{x}_0$；另一常见错误是将系数向量的顺序写反，误写为$k(1, -2, 1)^T$或$k(1, 2, -1)^T$等。",
        "computational_workload": "低"
      },
      "is_multiple_choice": false
    },
    {
      "question_number": "14",
      "question_body": "设随机变量 $X$ 的概率密度为 $f(x) = \\begin{cases} \\frac{x}{2}, & 0 < x < 2, \\\\ 0, & \\text{其他,} \\end{cases}$ $F(x)$ 为 $X$ 的分布函数，$E(X)$ 为 $X$ 的数学期望，则 $P\\{F(X) > E(X) - 1\\} = $______.",
      "options": {},
      "analysis": {
        "primary_knowledge_point": "分布函数的定义和性质，特别是概率$P\\{g(X) \\le y\\}$的计算",
        "secondary_knowledge_points": [
          "连续型随机变量数学期望的定义与计算",
          "概率密度的性质",
          "分段函数的处理",
          "不等式在随机变量函数下的概率求解"
        ],
        "question_type": "随机变量函数的概率计算",
        "methodology_and_tricks": "解题关键是理解 $F(X)$ 作为一个随机变量，其取值范围在 [0,1] 区间内。通过计算 $E(X)$ 和求出 $F(x)$ 的显式表达式，将概率 $P\\{F(X) > E(X)-1\\}$ 转换为 $P\\{X > a\\}$ 的形式，从而利用分布函数求解。",
        "common_pitfalls": "考生容易错误地将 $F(X) > E(X)-1$ 直接当作关于 $X$ 的不等式求解，而忽略了 $F(X)$ 本身的性质（如 $0 \\le F(X) \\le 1$）以及 $E(X)-1$ 可能超出 [0,1] 区间的情况。另一个常见错误是分布函数 $F(x)$ 计算错误或数学期望 $E(X)$ 计算错误。",
        "computational_workload": "中"
      },
      "is_multiple_choice": false
    },
    {
      "question_number": "15",
      "question_body": "设函数 $y(x)$ 是微分方程 $y' + xy = e^{-\\frac{x^2}{2}}$ 满足条件 $y(0) = 0$ 的特解.\\n(I) 求 $y(x)$;\\n(II) 求曲线 $y = y(x)$ 的凹凸区间及拐点.",
      "options": {},
      "analysis": {
        "primary_knowledge_point": "一阶线性微分方程的求解公式",
        "secondary_knowledge_points": [
          "导数的运算（含乘积法则）",
          "函数的凹凸性与拐点的定义及判别法",
          "指数函数的积分"
        ],
        "question_type": "微分方程求解与函数性质分析题",
        "methodology_and_tricks": "第一问使用一阶线性微分方程的标准解法（通解公式），并结合初值条件求特解；第二问基于第一问的解求二阶导数，通过判断其二阶导数的符号变化来研究凹凸性与拐点。题眼在于正确运用通解公式并准确计算积分。",
        "common_pitfalls": "在计算积分因子时忽略指数部分的符号或系数；求解特解后忘记应用初值条件确定常数；在求凹凸区间时，对二阶导数的正负与凹凸性的对应关系（上凹/下凸与二阶导正负的对应）记忆混淆；忽略拐点定义中要求函数在该点连续且二阶导数变号。",
        "computational_workload": "中"
      },
      "is_multiple_choice": false
    },
    {
      "question_number": "16",
      "question_body": "设 $a, b$ 为实数，函数 $z = 2 + ax^2 + by^2$ 在点 $(3, 4)$ 处的方向导数中，沿方向 $\\mathbf{l} = -3\\mathbf{i} - 4\\mathbf{j}$ 的方向导数最大，最大值为 $10$.\\n(I) 求 $a, b$;\\n(II) 求曲面 $z = 2 + ax^2 + by^2(z \\ge 0)$ 的面积.",
      "options": {},
      "analysis": {
        "primary_knowledge_point": "方向导数的最大值与梯度的关系（梯度的模等于方向导数的最大值，方向为梯度方向本身）",
        "secondary_knowledge_points": [
          "偏导数的计算",
          "梯度向量的定义",
          "曲面的面积计算公式（对于显式函数 z=f(x,y)）",
          "二重积分的计算（极坐标变换）"
        ],
        "question_type": "多元函数微分学与几何应用综合题",
        "methodology_and_tricks": "题眼在于理解‘方向导数最大’的条件。这意味着题目给定的方向 l 就是梯度向量的方向，且梯度的模等于最大值10。由此可建立关于a, b的方程组。第二部分曲面积分的计算区域由 z>=0 决定，本质上是求解投影区域上的二重积分。",
        "common_pitfalls": "1. 混淆方向导数与梯度的概念，未能建立‘最大方向导数对应梯度模’这一关键等式。2. 在计算梯度时出现符号或计算错误。3. 在第二部分求解曲面积分时，忽视积分区域由 z>=0 (即 2+ax^2+by^2>=0) 所定义的条件，导致积分区域判断错误。4. 在极坐标变换后，对角度θ和半径ρ的积分上下限确定错误。",
        "computational_workload": "中"
      },
      "is_multiple_choice": false
    },
    {
      "question_number": "17",
      "question_body": "求曲线 $y = e^{-x}\\sin x(x \\ge 0)$ 与 $x$ 轴之间图形的面积。",
      "options": {},
      "analysis": {
        "primary_knowledge_point": "定积分在几何学上的应用——平面图形的面积",
        "secondary_knowledge_points": [
          "分部积分法",
          "绝对值的定积分处理",
          "反常积分的计算"
        ],
        "question_type": "定积分几何应用题",
        "methodology_and_tricks": "该题的关键在于认识到曲线与x轴围成的图形面积并非单段，而是由无穷多个波瓣（即曲线与x轴在区间[kπ, (k+1)π]上围成的图形）组成。因此，总面积是所有这些波瓣面积之和，需要计算一个无穷级数。解题的核心技巧是先利用对称性计算一个典型波瓣（例如第一个波瓣）的面积，然后利用级数求和得到总面积。在处理一个波瓣的定积分 ∫ e^{-x} |sin x| dx 时，通过分析函数在区间[0, π]上 sin x ≥ 0 的特性去掉绝对值，并巧妙地运用两次分部积分来求解定积分。",
        "common_pitfalls": "1. 最典型的错误是直接计算反常积分 ∫(0 to +∞) e^{-x} sin x dx。虽然该积分可求且收敛，但其结果（1/2）是函数与x轴所围成图形的‘代数和’（有正有负相互抵消），而非‘面积总和’。面积必须是正的，所以必须对被积函数取绝对值，即计算 ∫(0 to +∞) e^{-x} |sin x| dx。2. 在计算 ∫ e^{-x} |sin x| dx 时，未能正确处理绝对值符号，导致积分区域划分错误。3. 在利用 e^{-x} 的衰减性对级数求和时，可能会忽略其作为几何级数的公比，导致求和公式错误。",
        "computational_workload": "中"
      },
      "is_multiple_choice": false
    },
    {
      "question_number": "18",
      "question_body": "设 $a_n = \\int_{0}^{1} x^n\\sqrt{1 - x^2}dx(n = 0, 1, 2, \\dots)$。\n(I) 证明数列 $\\{a_n\\}$ 单调递减,且 $a_n = \\frac{n - 1}{n + 2} a_{n-2}(n = 2, 3, \\dots)$;\n(II) 求 $\\lim_{n\\to\\infty} \\frac{a_n}{a_{n-1}}$。",
      "options": {},
      "analysis": {
        "primary_knowledge_point": "定积分的递推关系与积分渐近分析",
        "secondary_knowledge_points": [
          "分部积分法",
          "定积分的比较性质",
          "最大项原理/积分中值定理的极限应用",
          "施笃兹定理或极限比值的渐近分析"
        ],
        "question_type": "积分极限与递推关系的证明与计算题",
        "methodology_and_tricks": "通过分部积分消去被积函数中的x^n，建立相邻项的递推关系；对于极限问题，利用递推关系转化为相邻项的比值分析，结合积分的渐近估计或施笃兹定理确定极限。关键技巧是将a_n/a_{n-1}转化为已知递推式的线性组合，从而避开直接计算积分的复杂性。",
        "common_pitfalls": "在建立递推关系时未正确处理边界项导致关系错误；在求极限时误认为a_n单调递减故比值极限直接为0（实际上需考虑渐近阶的分析）；忽略n的奇偶性对递推初始值的影响（尽管本题极限计算中可忽略）。",
        "computational_workload": "中"
      },
      "is_multiple_choice": false
    },
    {
      "question_number": "19",
      "question_body": "设 $\\Omega$ 是由锥面 $x^2 + (y - z)^2 = (1 - z)^2(0 \\le z \\le 1)$ 与平面 $z = 0$ 围成的锥体,求 $\\Omega$ 的形心坐标。",
      "options": {},
      "analysis": {
        "primary_knowledge_point": "三重积分计算形心坐标",
        "secondary_knowledge_points": [
          "三重积分在柱坐标系/直角坐标系下的计算",
          "锥体体积公式",
          "被积函数的奇偶性分析",
          "对称性在积分中的应用",
          "积分区域的确定与投影"
        ],
        "question_type": "三重积分应用题",
        "methodology_and_tricks": "识别锥体对称性（关于y-z平面不对称，但关于x=0平面对称），利用对称性简化计算（形心的x坐标为0）。关键在于通过锥面方程分析区域Ω在z高度处的截面形状，并将其投影到xy平面以设置积分限。",
        "common_pitfalls": "1) 错误判断对称性导致形心坐标计算错误；2) 锥面方程化简或截面半径提取错误；3) 积分区域设置不准确，特别是z的积分上下限混淆；4) 计算三重积分时忘记雅可比系数。",
        "computational_workload": "中"
      },
      "is_multiple_choice": false
    },
    {
      "question_number": "20",
      "question_body": "设向量组 $\\alpha_1 = (1, 2, 1)^{\\text{T}}$, $\\alpha_2 = (1, 3, 2)^{\\text{T}}$, $\\alpha_3 = (1, a, 3)^{\\text{T}}$ 为 $\\mathbf{R}^3$ 的一个基, $\\boldsymbol{\\beta} = (1, 1, 1)^{\\text{T}}$ 在这个基下的坐标为 $(b, c, 1)^{\\text{T}}$。\n(I) 求 $a, b, c$;\n(II) 证明 $\\boldsymbol{\\alpha}_2, \\boldsymbol{\\alpha}_3, \\boldsymbol{\\beta}$ 为 $\\mathbf{R}^3$ 的一个基,并求 $\\boldsymbol{\\alpha}_2, \\boldsymbol{\\alpha}_3, \\boldsymbol{\\beta}$ 到 $\\boldsymbol{\\alpha}_1, \\boldsymbol{\\alpha}_2, \\boldsymbol{\\alpha}_3$ 的过渡矩阵。",
      "options": {},
      "analysis": {
        "primary_knowledge_point": "过渡矩阵的定义与性质",
        "secondary_knowledge_points": [
          "向量组线性相关性与基的判定",
          "向量在基下的坐标定义",
          "矩阵的秩与可逆性",
          "线性方程组的求解"
        ],
        "question_type": "过渡矩阵与向量坐标求解",
        "methodology_and_tricks": "利用向量在不同基下的坐标关系建立方程。题眼是通过已知条件构建方程：由基α下的坐标表示β，得到 α_1, α_2, α_3 矩阵与坐标向量的乘积等于β；再基于α是基可确定a的范围并解出a, b, c。第二部分利用过渡矩阵定义和矩阵分块计算。",
        "common_pitfalls": "混淆过渡矩阵的方向（题目要求从α2, α3, β到α1, α2, α3的过渡矩阵），忽略基的判定条件（向量组线性无关且个数=维数），以及在计算过渡矩阵时未正确设置坐标关系式。",
        "computational_workload": "中"
      },
      "is_multiple_choice": false
    },
    {
      "question_number": "21",
      "question_body": "已知矩阵 $A = \\begin{pmatrix} -2 & -2 & 1 \\\\ 2 & x & -2 \\\\ 0 & 0 & -2 \\end{pmatrix}$ 与 $B = \\begin{pmatrix} 2 & 1 & 0 \\\\ 0 & -1 & 0 \\\\ 0 & 0 & y \\end{pmatrix}$ 相似.\\\\ ( I ) 求 $x,y$;\\\\ ( II ) 求可逆矩阵 $P$ 使得 $P^{-1}AP = B$.",
      "options": {},
      "analysis": {
        "primary_knowledge_point": "矩阵相似的定义与性质。相似矩阵具有相同的迹、行列式和特征值。",
        "secondary_knowledge_points": [
          "特征值与特征向量的计算",
          "矩阵对角化理论",
          "线性方程组的求解",
          "矩阵的秩"
        ],
        "question_type": "矩阵相似问题求解",
        "methodology_and_tricks": "题眼在于利用相似矩阵的性质建立关于x, y的方程组。首先，通过迹相等和行列式相等这两个独立条件联立求解x和y。然后，对于第二问，通过求解矩阵A的特征值和特征向量，并根据矩阵B的结构（分块对角矩阵）来构造可逆矩阵P。",
        "common_pitfalls": "1. 混淆矩阵相似与矩阵等价或合同的性质，错误地使用秩相等作为求解条件。2. 在利用迹和行列式建立方程时出现计算错误。3. 在求解特征向量时，忽略B的块结构（前两列对应特征值2和-1的广义特征向量），导致无法正确构造P。4. 忽略特征向量的线性无关性验证。",
        "computational_workload": "中"
      },
      "is_multiple_choice": false
    },
    {
      "question_number": "22",
      "question_body": "设随机变量 $X$ 与 $Y$ 相互独立, $X$ 服从参数为 $1$ 的指数分布, $Y$ 的概率分布为 $P\\{Y = -1\\} = p, P\\{Y = 1\\} = 1 - p(0 < p < 1)$. 令 $Z = XY$. \\\\ ( I ) 求 $Z$ 的概率密度;\\\\ ( II ) $p$ 为何值时, $X$ 与 $Z$ 不相关;\\\\ ( III ) $X$ 与 $Z$ 是否相互独立?",
      "options": {},
      "analysis": {
        "primary_knowledge_point": "二维随机变量函数的分布（连续与离散混合型）",
        "secondary_knowledge_points": [
          "指数分布的概率密度与性质",
          "随机变量的独立性",
          "协方差与相关系数的计算",
          "全概率公式"
        ],
        "question_type": "二维随机变量函数的分布与独立性判断",
        "methodology_and_tricks": "题眼在于处理连续型随机变量$X$与离散型随机变量$Y$的乘积$Z=XY$。对于(I)，应使用全概率公式，将$Z$的概率密度拆分为$Y=-1$和$Y=1$两种情况分别讨论，再合并结果。对于(II)，利用不相关即协方差为零的性质，$Cov(X,Z)=E(XZ)-E(X)E(Z)$。对于(III)，通过判断$P(X \\le x, Z \\le z)$是否等于$P(X \\le x)P(Z \\le z)$来验证独立性。",
        "common_pitfalls": "1. 忽略$Y$的离散性，错误地使用卷积公式直接计算$Z$的概率密度。2. 在计算$E(XZ)$时，未能利用$X$与$Y$的独立性进行化简。3. 在判断独立性时，仅通过不相关（协方差为零）就草率得出结论，而忽略了对于非正态分布，不相关不一定意味着独立。",
        "computational_workload": "中"
      },
      "is_multiple_choice": false
    },
    {
      "question_number": "23",
      "question_body": "设总体 $X$ 的概率密度为 \\\\ $f(x; \\sigma^2) = \\begin{cases} \\frac{A}{\\sigma}e^{-\\frac{(x-\\mu)^2}{2\\sigma^2}}, & x \\ge \\mu \\\\ 0, & x < \\mu \\end{cases}$ \\\\ 其中 $\\mu$ 是已知参数, $\\sigma > 0$ 是未知参数, $A$ 是常数. $X_1, X_2, \\dots, X_n$ 是来自总体 $X$ 的简单随机样本. \\\\ ( I ) 求 $A$;\\\\ ( II ) 求 $\\sigma^2$ 的最大似然估计量.",
      "options": {},
      "analysis": {
        "primary_knowledge_point": "最大似然估计",
        "secondary_knowledge_points": [
          "概率密度的归一性条件",
          "含参变量积分的计算",
          "对数似然函数的构建与求导",
          "截断正态分布的性质"
        ],
        "question_type": "参数估计综合题",
        "methodology_and_tricks": "题目的关键在于识别出概率密度是截断正态分布（仅保留x≥μ的部分）。(I) 利用概率密度全域积分为1的归一性条件求解常数A。(II) 构建似然函数时，由于样本点均需满足x_i ≥ μ（否则似然函数为0），可直接基于x_i ≥ μ的样本写出似然函数，再通过求导求极值的方法求解σ²的最大似然估计。",
        "common_pitfalls": "1. 在(I)部分积分计算错误，未能正确得到A与σ无关的结论。2. 在(II)部分构建似然函数时，忽略样本必须满足x_i ≥ μ的条件，错误地将定义域x<μ的部分（概率密度为0）也纳入考虑，导致求解过程复杂化或错误。3. 对似然函数取对数后求导时，未能正确处理σ²作为整体参数进行求导的运算。",
        "computational_workload": "中"
      },
      "is_multiple_choice": false
    }
  ],
  "summary": {
    "overview": {
      "subject_domain": "考研数学一",
      "total_questions": 23,
      "overall_difficulty_assessment": "试卷整体难度中等偏上，考查全面，综合性较强，尤其注重对基本概念、定理和计算能力的考查。"
    },
    "module_weight_analysis": [
      {
        "module": "高等数学-微积分",
        "count": 9,
        "percentage": "39.1%"
      },
      {
        "module": "高等数学-无穷级数",
        "count": 2,
        "percentage": "8.7%"
      },
      {
        "module": "高等数学-微分方程",
        "count": 2,
        "percentage": "8.7%"
      },
      {
        "module": "高等数学-多元函数微积分",
        "count": 4,
        "percentage": "17.4%"
      },
      {
        "module": "线性代数",
        "count": 4,
        "percentage": "17.4%"
      },
      {
        "module": "概率论与数理统计",
        "count": 4,
        "percentage": "17.4%"
      }
    ],
    "synthesis_and_flexibility_analysis": "本次考试对知识网络的构建和综合运用能力要求较高。约有30%的题目（如题(16)、(19)、(20)、(22)）需要综合运用多个章节的知识点进行求解，要求考生具备良好的知识迁移和灵活应用能力。",
    "computational_skills_diagnosis": "试卷整体计算量中等，但对计算的准确性要求高。微积分的计算（如分部积分、曲面积分）和线性代数的矩阵运算（如特征值、过渡矩阵）是计算的重点和易错点，步骤繁琐，极易因符号或代数变形错误导致失分。",
    "strategic_recommendations": {
      "focus_areas": [
        "多元函数微积分（方向导数、曲面积分）",
        "线性代数（矩阵相似、过渡矩阵）",
        "概率论（随机变量函数的分布）",
        "微分方程求解与性质分析",
        "无穷级数与幂级数求和"
      ],
      "predicted_pitfalls_summary": [
        "定积分计算中忽略绝对值导致面积计算错误（题17）",
        "矩阵运算中特征值求解与验证错误（题21）",
        "曲面积分投影方向与符号处理错误（题12）",
        "随机变量函数分布求解时忽略变量类型（连续/离散）导致方法错误（题22）"
      ],
      "improvement_suggestions": "加强基本概念的理解和辨析，如方向导数与梯度的关系、矩阵相似的性质；提高复杂计算的准确性和熟练度，尤其是分部积分和多重积分；注重解题规范，避免因步骤省略或符号错误导致失分。"
    }
  }
}